ssNMR/__init__.py
ssNMR/fitting.py
ssNMR/formatting.py
ssnmr-1.1.0.dist-info/LICENSE
ssnmr-1.1.0.dist-info/METADATA
ssnmr-1.1.0.dist-info/WHEEL
ssnmr-1.1.0.dist-info/top_level.txt
ssnmr-1.1.0.dist-info/RECORD
