Metadata-Version: 2.1
Name: ssnmr
Version: 1.1.0
Summary: A pythonic way to fit solid-state NMR spectra
Author-email: Vincent Wu <vincentwu@berkeley.edu>
License: MIT License
Project-URL: Homepage, https://github.com/vince-wu/ssNMR-fitting
Keywords: NMR,fit,dmfit
Classifier: License :: OSI Approved :: MIT License
Classifier: Programming Language :: Python
Classifier: Programming Language :: Python :: 3
Requires-Python: >=3.6
License-File: LICENSE
Requires-Dist: matplotlib >=3.0.0
Requires-Dist: numpy >=1.0.0
Requires-Dist: scipy >=1.0.0
Requires-Dist: lmfit >=1.0.3
Requires-Dist: pandas >=1.0.0
Requires-Dist: seaborn
Provides-Extra: dev
